{"name":"build-javascript","namedChunkGroups":{"app":{"name":"app","assets":[{"name":"webpack-runtime-fcbc301bad4b5d23f63a.js","size":4984},{"name":"framework-6a525285796fb83f2864.js","size":140785},{"name":"app-cc0d7db1a2f50ec8676b.js","size":68255}],"filteredAssets":0,"assetsSize":214024,"filteredAuxiliaryAssets":3,"auxiliaryAssetsSize":616622},"component---src-pages-404-js":{"name":"component---src-pages-404-js","assets":[{"name":"styles.2b97ac019eb767680ed0.css","size":12612},{"name":"c16184b3-c19bf6f0f413dcf09897.js","size":934},{"name":"2cca2479-dde17cd2b4839066b23a.js","size":3180},{"name":"commons-343e7983c0ef20ff5c03.js","size":114169},{"name":"component---src-pages-404-js-262b8f85602e8ab027c9.js","size":1364}],"filteredAssets":0,"assetsSize":132259,"filteredAuxiliaryAssets":4,"auxiliaryAssetsSize":1969969},"component---src-pages-index-jsx":{"name":"component---src-pages-index-jsx","assets":[{"name":"styles.2b97ac019eb767680ed0.css","size":12612},{"name":"c16184b3-c19bf6f0f413dcf09897.js","size":934},{"name":"2cca2479-dde17cd2b4839066b23a.js","size":3180},{"name":"commons-343e7983c0ef20ff5c03.js","size":114169},{"name":"component---src-pages-index-jsx-e8cc870b1a0a57d66c25.js","size":433}],"filteredAssets":0,"assetsSize":131328,"filteredAuxiliaryAssets":4,"auxiliaryAssetsSize":1968155},"component---src-pages-markdown-remark-fields-slug-jsx":{"name":"component---src-pages-markdown-remark-fields-slug-jsx","assets":[{"name":"styles.2b97ac019eb767680ed0.css","size":12612},{"name":"c16184b3-c19bf6f0f413dcf09897.js","size":934},{"name":"2cca2479-dde17cd2b4839066b23a.js","size":3180},{"name":"commons-343e7983c0ef20ff5c03.js","size":114169},{"name":"component---src-pages-markdown-remark-fields-slug-jsx-1c3ca8403401561fb2a2.js","size":529}],"filteredAssets":0,"assetsSize":131424,"filteredAuxiliaryAssets":4,"auxiliaryAssetsSize":1968400}},"assetsByChunkName":{"app":["webpack-runtime-fcbc301bad4b5d23f63a.js","framework-6a525285796fb83f2864.js","app-cc0d7db1a2f50ec8676b.js"],"component---src-pages-404-js":["styles.2b97ac019eb767680ed0.css","c16184b3-c19bf6f0f413dcf09897.js","2cca2479-dde17cd2b4839066b23a.js","commons-343e7983c0ef20ff5c03.js","component---src-pages-404-js-262b8f85602e8ab027c9.js"],"component---src-pages-index-jsx":["styles.2b97ac019eb767680ed0.css","c16184b3-c19bf6f0f413dcf09897.js","2cca2479-dde17cd2b4839066b23a.js","commons-343e7983c0ef20ff5c03.js","component---src-pages-index-jsx-e8cc870b1a0a57d66c25.js"],"component---src-pages-markdown-remark-fields-slug-jsx":["styles.2b97ac019eb767680ed0.css","c16184b3-c19bf6f0f413dcf09897.js","2cca2479-dde17cd2b4839066b23a.js","commons-343e7983c0ef20ff5c03.js","component---src-pages-markdown-remark-fields-slug-jsx-1c3ca8403401561fb2a2.js"]},"childAssetsByChunkName":{}}